pytest_dotenv_modern/__init__.py
pytest_dotenv_modern/plugin.py
pytest_dotenv_modern-0.3.0.dist-info/METADATA
pytest_dotenv_modern-0.3.0.dist-info/WHEEL
pytest_dotenv_modern-0.3.0.dist-info/entry_points.txt
pytest_dotenv_modern-0.3.0.dist-info/top_level.txt
pytest_dotenv_modern-0.3.0.dist-info/RECORD
