Metadata-Version: 2.4
Name: pytest-dotenv-modern
Version: 0.3.0
Summary: A modern pytest plugin that loads environment variables from dotenv files
Author-email: Your Name <your.email@example.com>
License: MIT
Project-URL: Homepage, https://github.com/jobissjo/pytest-dotenv-modern
Project-URL: Repository, https://github.com/jobissjo/pytest-dotenv-modern
Project-URL: Issues, https://github.com/jobissjo/pytest-dotenv-modern/issues
Keywords: pytest,dotenv,environment,testing
Classifier: Development Status :: 4 - Beta
Classifier: Framework :: Pytest
Classifier: Intended Audience :: Developers
Classifier: License :: OSI Approved :: MIT License
Classifier: Operating System :: OS Independent
Classifier: Programming Language :: Python
Classifier: Programming Language :: Python :: 3
Classifier: Programming Language :: Python :: 3.8
Classifier: Programming Language :: Python :: 3.9
Classifier: Programming Language :: Python :: 3.10
Classifier: Programming Language :: Python :: 3.11
Classifier: Programming Language :: Python :: 3.12
Classifier: Topic :: Software Development :: Testing
Requires-Python: >=3.11
Requires-Dist: pytest>=6.0.0
Requires-Dist: python-dotenv>=0.5.0
Requires-Dist: tomli>=1.2.0
Provides-Extra: dev
Requires-Dist: pytest-cov; extra == "dev"
Requires-Dist: black; extra == "dev"
Requires-Dist: isort; extra == "dev"
Requires-Dist: flake8; extra == "dev"
Requires-Dist: mypy; extra == "dev"
Requires-Dist: pre-commit; extra == "dev"
